{
  "index": 399,
  "id": 6341,
  "folder": "0399-the-ufos-night-in-brazil-1986-documents-2",
  "slug": "the-ufos-night-in-brazil-1986-documents-2",
  "title": "“THE UFOS’ NIGHT IN BRAZIL” [1986] – Documents #2",
  "date": "2020-07-11T15:22:59-03:00",
  "modified": "2020-07-23T19:54:33-03:00",
  "url": "http://brazilianufoarchives.com/2020/07/11/the-ufos-night-in-brazil-1986-documents-2/",
  "categories": [
    "Sem categoria"
  ],
  "tags": [],
  "excerpt": "Brasília-DF, May 27, 1986. From: 1st TEN ESP CTA F. H.N. FREITAS. To: Mr. HEAD OF COpM1 INFORMATION SECTION. Subject: Possible appearance of UFOs in SBSJ and SBAN. I – I report to you, for the appropriate purposes, the events of 19 MAY 86 – 23: 15Z to 20 MAY 86 03: 32Z: “ACC BR […]",
  "image_count": 0,
  "images": [],
  "thumbnail": null,
  "word_count": 1380,
  "text_preview": "Brasília-DF, May 27, 1986.\n\nFrom: 1st TEN ESP CTA F. H.N. FREITAS.\n\nTo: Mr. HEAD OF COpM1 INFORMATION SECTION.\n\nSubject: Possible appearance of UFOs in SBSJ and SBAN.\n\n## I – I report to you, for the appropriate purposes, the events of 19 MAY 86 – 23: 15Z to 20 MAY 86 03: 32Z: \n\n“ACC BR (CTA BUENO) informed COpMI that the operator of TWRSJ, 2S QSS BCT S.M. DA SILVA, was seeing lights over the city and close to the external marker of RWY 15. The ACC BS also reported that APP-SP obtained radar contact with some targets in the vicinity of SBSJ.\n\n– COpM I (SGT EMILIO) contacted TWR SJ and received",
  "sighting_year": 1986,
  "location": "São José dos Campos",
  "state": "SP",
  "craft_shape": "light",
  "occupants": false,
  "effects": [
    "electromagnetic"
  ],
  "source_type": "official-military-report",
  "summary": "CTA officer's detailed report on the May 19-20, 1986 UFO Night, with 5 FAB fighter scrambles, radar plots near SBSJ and Anápolis, and failed interception attempts.",
  "keywords": [
    "ufo night brazil",
    "interception",
    "radar plots",
    "fab scramble",
    "1986",
    "anapolis"
  ]
}